code/__init__.py
code/graphbar.py
graphbar-0.0.2.dist-info/LICENSE
graphbar-0.0.2.dist-info/METADATA
graphbar-0.0.2.dist-info/WHEEL
graphbar-0.0.2.dist-info/top_level.txt
graphbar-0.0.2.dist-info/RECORD
