Metadata-Version: 2.1
Name: graphbar
Version: 0.0.2
Summary: Make bar graph by groups
Home-page: https://github.com/manuelgilm/graphbar
Author: Manuel Gil
Author-email: manuelgilsitio@gmail.com
License: UNKNOWN
Platform: UNKNOWN
Classifier: Programming Language :: Python :: 3
Classifier: License :: OSI Approved :: MIT License
Classifier: Operating System :: OS Independent
Requires-Python: >=3.6
